LICENSE
MANIFEST.in
Readme.md
setup.cfg
setup.py
sociophysicsDataHandler/__init__.py
sociophysicsDataHandler/ddut.py
sociophysicsDataHandler/spdh.py
sociophysicsDataHandler.egg-info/PKG-INFO
sociophysicsDataHandler.egg-info/SOURCES.txt
sociophysicsDataHandler.egg-info/dependency_links.txt
sociophysicsDataHandler.egg-info/requires.txt
sociophysicsDataHandler.egg-info/top_level.txt