Metadata-Version: 2.1
Name: sociophysicsDataHandler
Version: 1.1.0
Summary: Data retriever package for the Sociophysics course at TU/Eindhoven.
Home-page: https://github.com/acorbe/sociophysicsDataHandler
Author: Alessandro Corbetta; Cas Pouw; Joris Willems
Author-email: a.corbetta@tue.nl
License: new BSD
Platform: UNKNOWN
